oscb/__init__.py
oscb/version.py
oscb/clustering/__init__.py
oscb/clustering/clustering_analysis.py
oscb/clustering/run_clustering.py
oscb/download_dataset/__init__.py
oscb/download_dataset/download_file.py
oscb/download_dataset/download_utils.py
oscb-2.0.2.dist-info/METADATA
oscb-2.0.2.dist-info/WHEEL
oscb-2.0.2.dist-info/top_level.txt
oscb-2.0.2.dist-info/RECORD
